dicttoobject/__init__.py
dicttoobject/converter.py
dicttoobject/error.py
dicttoobject/type.py
dict_to_object-1.0.3.dist-info/LICENSE
dict_to_object-1.0.3.dist-info/METADATA
dict_to_object-1.0.3.dist-info/WHEEL
dict_to_object-1.0.3.dist-info/top_level.txt
dict_to_object-1.0.3.dist-info/RECORD
