Metadata-Version: 2.1
Name: dict-to-object
Version: 1.0.3
Summary: python dictionary to object.
Home-page: https://github.com/oneofthezombies/dict-to-object
Author: oneofthezombies
Author-email: hunhoekim@gmail.com
License: MIT
Platform: UNKNOWN
Classifier: Programming Language :: Python :: 3
Classifier: License :: OSI Approved :: MIT License
Classifier: Operating System :: OS Independent
